[
  {
    "params": {
      "num_layers": 2,
      "n_hidden": 24,
      "lr": 0.00020691380811147902,
      "dropout": 0.1
    },
    "mse": 0.2348175048828125
  },
  {
    "params": {
      "num_layers": 1,
      "n_hidden": 32,
      "lr": 0.0006951927961775605,
      "dropout": 0.3
    },
    "mse": 0.0732637271285057
  },
  {
    "params": {
      "num_layers": 2,
      "n_hidden": 8,
      "lr": 0.0001623776739188721,
      "dropout": 0.1
    },
    "mse": 0.2649807333946228
  },
  {
    "params": {
      "num_layers": 1,
      "n_hidden": 28,
      "lr": 0.0014384498882876629,
      "dropout": 0.2
    },
    "mse": 0.04499262943863869
  },
  {
    "params": {
      "num_layers": 2,
      "n_hidden": 12,
      "lr": 0.0003359818286283781,
      "dropout": 0.2
    },
    "mse": 0.22147849202156067
  },
  {
    "params": {
      "num_layers": 3,
      "n_hidden": 28,
      "lr": 0.00026366508987303583,
      "dropout": 0.1
    },
    "mse": 0.2164391577243805
  },
  {
    "params": {
      "num_layers": 3,
      "n_hidden": 12,
      "lr": 0.00020691380811147902,
      "dropout": 0.3
    },
    "mse": 0.2542645037174225
  },
  {
    "params": {
      "num_layers": 2,
      "n_hidden": 16,
      "lr": 0.007847599703514606,
      "dropout": 0.3
    },
    "mse": 0.03801807016134262
  },
  {
    "params": {
      "num_layers": 1,
      "n_hidden": 8,
      "lr": 0.00615848211066026,
      "dropout": 0.2
    },
    "mse": 0.0393393412232399
  },
  {
    "params": {
      "num_layers": 1,
      "n_hidden": 24,
      "lr": 0.00012742749857031334,
      "dropout": 0.2
    },
    "mse": 0.25613415241241455
  },
  {
    "params": {
      "num_layers": 1,
      "n_hidden": 8,
      "lr": 0.00020691380811147902,
      "dropout": 0.1
    },
    "mse": 0.24451066553592682
  },
  {
    "params": {
      "num_layers": 3,
      "n_hidden": 8,
      "lr": 0.0003359818286283781,
      "dropout": 0.3
    },
    "mse": 0.23164354264736176
  },
  {
    "params": {
      "num_layers": 3,
      "n_hidden": 24,
      "lr": 0.004832930238571752,
      "dropout": 0.1
    },
    "mse": 0.037897102534770966
  },
  {
    "params": {
      "num_layers": 1,
      "n_hidden": 32,
      "lr": 0.00026366508987303583,
      "dropout": 0.2
    },
    "mse": 0.21097692847251892
  },
  {
    "params": {
      "num_layers": 2,
      "n_hidden": 12,
      "lr": 0.00020691380811147902,
      "dropout": 0.3
    },
    "mse": 0.2521568536758423
  },
  {
    "params": {
      "num_layers": 1,
      "n_hidden": 8,
      "lr": 0.0018329807108324356,
      "dropout": 0.2
    },
    "mse": 0.050895240157842636
  },
  {
    "params": {
      "num_layers": 3,
      "n_hidden": 32,
      "lr": 0.007847599703514606,
      "dropout": 0.1
    },
    "mse": 0.03790618106722832
  },
  {
    "params": {
      "num_layers": 1,
      "n_hidden": 16,
      "lr": 0.01,
      "dropout": 0.2
    },
    "mse": 0.038233160972595215
  },
  {
    "params": {
      "num_layers": 2,
      "n_hidden": 12,
      "lr": 0.00615848211066026,
      "dropout": 0.1
    },
    "mse": 0.03812550753355026
  },
  {
    "params": {
      "num_layers": 2,
      "n_hidden": 28,
      "lr": 0.00615848211066026,
      "dropout": 0.2
    },
    "mse": 0.03801337257027626
  },
  {
    "params": {
      "num_layers": 1,
      "n_hidden": 20,
      "lr": 0.00026366508987303583,
      "dropout": 0.3
    },
    "mse": 0.2177300751209259
  },
  {
    "params": {
      "num_layers": 1,
      "n_hidden": 20,
      "lr": 0.00026366508987303583,
      "dropout": 0.2
    },
    "mse": 0.22115927934646606
  },
  {
    "params": {
      "num_layers": 2,
      "n_hidden": 8,
      "lr": 0.0011288378916846883,
      "dropout": 0.2
    },
    "mse": 0.08283449709415436
  },
  {
    "params": {
      "num_layers": 1,
      "n_hidden": 12,
      "lr": 0.0001,
      "dropout": 0.3
    },
    "mse": 0.26906484365463257
  },
  {
    "params": {
      "num_layers": 3,
      "n_hidden": 20,
      "lr": 0.002976351441631319,
      "dropout": 0.3
    },
    "mse": 0.03875483572483063
  },
  {
    "params": {
      "num_layers": 3,
      "n_hidden": 12,
      "lr": 0.0006951927961775605,
      "dropout": 0.2
    },
    "mse": 0.12593884766101837
  },
  {
    "params": {
      "num_layers": 3,
      "n_hidden": 8,
      "lr": 0.0018329807108324356,
      "dropout": 0.1
    },
    "mse": 0.03993720933794975
  },
  {
    "params": {
      "num_layers": 1,
      "n_hidden": 32,
      "lr": 0.00020691380811147902,
      "dropout": 0.1
    },
    "mse": 0.22897839546203613
  },
  {
    "params": {
      "num_layers": 2,
      "n_hidden": 8,
      "lr": 0.0003359818286283781,
      "dropout": 0.2
    },
    "mse": 0.2305556684732437
  },
  {
    "params": {
      "num_layers": 3,
      "n_hidden": 24,
      "lr": 0.002976351441631319,
      "dropout": 0.1
    },
    "mse": 0.03816046938300133
  },
  {
    "params": {
      "num_layers": 2,
      "n_hidden": 20,
      "lr": 0.00615848211066026,
      "dropout": 0.1
    },
    "mse": 0.03811466321349144
  },
  {
    "params": {
      "num_layers": 2,
      "n_hidden": 32,
      "lr": 0.0003359818286283781,
      "dropout": 0.3
    },
    "mse": 0.17494073510169983
  },
  {
    "params": {
      "num_layers": 1,
      "n_hidden": 8,
      "lr": 0.002335721469090121,
      "dropout": 0.2
    },
    "mse": 0.04709745943546295
  },
  {
    "params": {
      "num_layers": 1,
      "n_hidden": 20,
      "lr": 0.004832930238571752,
      "dropout": 0.2
    },
    "mse": 0.0400056317448616
  },
  {
    "params": {
      "num_layers": 3,
      "n_hidden": 16,
      "lr": 0.0011288378916846883,
      "dropout": 0.3
    },
    "mse": 0.04231084883213043
  },
  {
    "params": {
      "num_layers": 3,
      "n_hidden": 28,
      "lr": 0.0001,
      "dropout": 0.3
    },
    "mse": 0.27225083112716675
  },
  {
    "params": {
      "num_layers": 2,
      "n_hidden": 16,
      "lr": 0.0018329807108324356,
      "dropout": 0.2
    },
    "mse": 0.040755078196525574
  },
  {
    "params": {
      "num_layers": 3,
      "n_hidden": 32,
      "lr": 0.000545559478116852,
      "dropout": 0.3
    },
    "mse": 0.058224935084581375
  },
  {
    "params": {
      "num_layers": 3,
      "n_hidden": 24,
      "lr": 0.007847599703514606,
      "dropout": 0.2
    },
    "mse": 0.037881843745708466
  },
  {
    "params": {
      "num_layers": 1,
      "n_hidden": 24,
      "lr": 0.0008858667904100823,
      "dropout": 0.2
    },
    "mse": 0.06044357270002365
  },
  {
    "params": {
      "num_layers": 3,
      "n_hidden": 16,
      "lr": 0.0008858667904100823,
      "dropout": 0.2
    },
    "mse": 0.04979705810546875
  },
  {
    "params": {
      "num_layers": 1,
      "n_hidden": 12,
      "lr": 0.0008858667904100823,
      "dropout": 0.1
    },
    "mse": 0.08833689242601395
  },
  {
    "params": {
      "num_layers": 1,
      "n_hidden": 28,
      "lr": 0.0001,
      "dropout": 0.2
    },
    "mse": 0.25884056091308594
  },
  {
    "params": {
      "num_layers": 2,
      "n_hidden": 24,
      "lr": 0.0018329807108324356,
      "dropout": 0.1
    },
    "mse": 0.040501829236745834
  },
  {
    "params": {
      "num_layers": 1,
      "n_hidden": 32,
      "lr": 0.0008858667904100823,
      "dropout": 0.3
    },
    "mse": 0.05814404785633087
  },
  {
    "params": {
      "num_layers": 1,
      "n_hidden": 28,
      "lr": 0.00020691380811147902,
      "dropout": 0.1
    },
    "mse": 0.22834832966327667
  },
  {
    "params": {
      "num_layers": 3,
      "n_hidden": 16,
      "lr": 0.0001,
      "dropout": 0.2
    },
    "mse": 0.2769731879234314
  },
  {
    "params": {
      "num_layers": 2,
      "n_hidden": 32,
      "lr": 0.0001,
      "dropout": 0.2
    },
    "mse": 0.2673955261707306
  },
  {
    "params": {
      "num_layers": 1,
      "n_hidden": 20,
      "lr": 0.002976351441631319,
      "dropout": 0.1
    },
    "mse": 0.04188041761517525
  },
  {
    "params": {
      "num_layers": 3,
      "n_hidden": 8,
      "lr": 0.002335721469090121,
      "dropout": 0.1
    },
    "mse": 0.039226554334163666
  },
  {
    "params": {
      "num_layers": 3,
      "n_hidden": 8,
      "lr": 0.007847599703514606,
      "dropout": 0.3
    },
    "mse": 0.038097791373729706
  },
  {
    "params": {
      "num_layers": 3,
      "n_hidden": 16,
      "lr": 0.000545559478116852,
      "dropout": 0.2
    },
    "mse": 0.14237076044082642
  },
  {
    "params": {
      "num_layers": 1,
      "n_hidden": 20,
      "lr": 0.0001623776739188721,
      "dropout": 0.1
    },
    "mse": 0.24252364039421082
  },
  {
    "params": {
      "num_layers": 1,
      "n_hidden": 20,
      "lr": 0.000545559478116852,
      "dropout": 0.3
    },
    "mse": 0.1369507908821106
  },
  {
    "params": {
      "num_layers": 1,
      "n_hidden": 12,
      "lr": 0.0003359818286283781,
      "dropout": 0.2
    },
    "mse": 0.20563088357448578
  },
  {
    "params": {
      "num_layers": 3,
      "n_hidden": 28,
      "lr": 0.01,
      "dropout": 0.3
    },
    "mse": 0.037898316979408264
  },
  {
    "params": {
      "num_layers": 2,
      "n_hidden": 32,
      "lr": 0.004832930238571752,
      "dropout": 0.3
    },
    "mse": 0.038179878145456314
  },
  {
    "params": {
      "num_layers": 2,
      "n_hidden": 28,
      "lr": 0.004832930238571752,
      "dropout": 0.1
    },
    "mse": 0.038275592029094696
  },
  {
    "params": {
      "num_layers": 3,
      "n_hidden": 20,
      "lr": 0.002335721469090121,
      "dropout": 0.3
    },
    "mse": 0.03883637860417366
  },
  {
    "params": {
      "num_layers": 3,
      "n_hidden": 16,
      "lr": 0.0001,
      "dropout": 0.3
    },
    "mse": 0.2752687633037567
  }
]